Metadata-Version: 1.0
Name: distgaubin
Version: 0.1
Summary: Gaussian and Binomial distributions
Home-page: UNKNOWN
Author: AnmolJM
Author-email: anmoljm@gmail.com
License: UNKNOWN
Platform: UNKNOWN
